cryton_cli/__init__.py
cryton_cli/etc/__init__.py
cryton_cli/etc/config.py
cryton_cli/lib/__init__.py
cryton_cli/lib/cli.py
cryton_cli/lib/commands/__init__.py
cryton_cli/lib/commands/dynamic_runs.py
cryton_cli/lib/commands/execution_variable.py
cryton_cli/lib/commands/log.py
cryton_cli/lib/commands/plan.py
cryton_cli/lib/commands/plan_template.py
cryton_cli/lib/commands/run.py
cryton_cli/lib/commands/stage.py
cryton_cli/lib/commands/step.py
cryton_cli/lib/commands/worker.py
cryton_cli/lib/util/__init__.py
cryton_cli/lib/util/api.py
cryton_cli/lib/util/constants.py
cryton_cli/lib/util/util.py
cryton_cli-2023.1.0.dist-info/entry_points.txt
cryton_cli-2023.1.0.dist-info/WHEEL
cryton_cli-2023.1.0.dist-info/METADATA
cryton_cli-2023.1.0.dist-info/LICENSE
cryton_cli-2023.1.0.dist-info/RECORD
