Metadata-Version: 2.1
Name: cryton-cli
Version: 2023.1.0
Summary: Command line interface for Cryton Core
Home-page: https://gitlab.ics.muni.cz/cryton
License: MIT
Keywords: cryton,cli,client
Author: Ivo Nutár
Author-email: nutar@ics.muni.cz
Maintainer: Jiří Rája
Maintainer-email: raja@ics.muni.cz
Requires-Python: >=3.8,<3.12
Classifier: License :: OSI Approved :: MIT License
Classifier: Programming Language :: Python :: 3
Classifier: Programming Language :: Python :: 3.8
Classifier: Programming Language :: Python :: 3.9
Classifier: Programming Language :: Python :: 3.10
Classifier: Programming Language :: Python :: 3.11
Requires-Dist: Jinja2 (>=3.0.3,<4.0.0)
Requires-Dist: PyYAML (>=6.0,<7.0)
Requires-Dist: click (>=8.1.2,<9.0.0)
Requires-Dist: pyfiglet (>=0.8.post1,<0.9)
Requires-Dist: python-dotenv (>=1.0.0,<2.0.0)
Requires-Dist: pytz (>=2022.7,<2023.0)
Requires-Dist: requests (>=2.27.0,<3.0.0)
Requires-Dist: termcolor (>=2.2.0,<3.0.0)
Requires-Dist: tzlocal (>=4.1,<5.0)
Project-URL: Documentation, https://cryton.gitlab-pages.ics.muni.cz/cryton-documentation/
Project-URL: Repository, https://gitlab.ics.muni.cz/cryton/cryton-cli
